onnx_embedding_models/__init__.py
onnx_embedding_models/crossencoder.py
onnx_embedding_models/embedding.py
onnx_embedding_models/registry.py
onnx_embedding_models/utils.py
onnx_embedding_models-0.0.16.dist-info/LICENSE
onnx_embedding_models-0.0.16.dist-info/METADATA
onnx_embedding_models-0.0.16.dist-info/WHEEL
onnx_embedding_models-0.0.16.dist-info/top_level.txt
onnx_embedding_models-0.0.16.dist-info/RECORD
