Metadata-Version: 2.1
Name: onnx_embedding_models
Version: 0.0.16
Summary: Python utility for text embeddings in ONNX.
Author-email: Benjamin Anderson <ben@trytaylor.ai>
Requires-Python: >=3.9
License-File: LICENSE
Requires-Dist: tqdm
Requires-Dist: onnxruntime
Requires-Dist: numpy<2
Requires-Dist: transformers>=4.44.0
Requires-Dist: huggingface-hub
Requires-Dist: scipy
